achat/__init__.py
achat/client.py
achat/errors.py
achat-0.1.0.dist-info/LICENSE
achat-0.1.0.dist-info/METADATA
achat-0.1.0.dist-info/WHEEL
achat-0.1.0.dist-info/RECORD
