Metadata-Version: 2.1
Name: achat
Version: 0.1.0
Summary: asynchronous wrapper over the chatsonic api for the python programming language
License: MIT
Author: saladware
Author-email: saladware46@gmail.com
Requires-Python: >=3.8,<4.0
Classifier: License :: OSI Approved :: MIT License
Classifier: Programming Language :: Python :: 3
Classifier: Programming Language :: Python :: 3.8
Classifier: Programming Language :: Python :: 3.9
Classifier: Programming Language :: Python :: 3.10
Classifier: Programming Language :: Python :: 3.11
Requires-Dist: aiohttp (>=3.8.4,<4.0.0)
